{
  "backup_wallet": {
    "string": ""
  },
  "backup_title": {
    "string": ""
  },
  "backup_funds": {
    "string": ""
  },
  "backup_funds_no": {
    "string": ""
  },
  "backup_button": {
    "string": ""
  },
  "pass": {
    "string": ""
  },
  "pass_your": {
    "string": ""
  },
  "pass_text": {
    "string": ""
  },
  "pass_never_share": {
    "string": ""
  },
  "pass_confirm": {
    "string": ""
  },
  "pass_confirm_text": {
    "string": ""
  },
  "pass_recovery": {
    "string": ""
  },
  "mnemonic_phrase": {
    "string": ""
  },
  "mnemonic_your": {
    "string": ""
  },
  "mnemonic_error": {
    "string": ""
  },
  "mnemonic_error_description": {
    "string": ""
  },
  "mnemonic_write": {
    "string": ""
  },
  "mnemonic_use": {
    "string": ""
  },
  "mnemonic_reveal": {
    "string": ""
  },
  "mnemonic_never_share": {
    "string": ""
  },
  "mnemonic_confirm": {
    "string": ""
  },
  "mnemonic_confirm_tap": {
    "string": ""
  },
  "mnemonic_result_header": {
    "string": ""
  },
  "mnemonic_result_text": {
    "string": ""
  },
  "mnemonic_keep_header": {
    "string": ""
  },
  "mnemonic_keep_text": {
    "string": ""
  },
  "mnemonic_data_header": {
    "string": ""
  },
  "mnemonic_data_text": {
    "string": ""
  },
  "mnemonic_multiple_header": {
    "string": ""
  },
  "mnemonic_multiple_text": {
    "string": ""
  },
  "mnemonic_latest_backup": {
    "string": ""
  },
  "pin_security_header": {
    "string": ""
  },
  "pin_security_title": {
    "string": ""
  },
  "pin_security_text": {
    "string": ""
  },
  "pin_security_button": {
    "string": ""
  },
  "pin_choose_header": {
    "string": ""
  },
  "pin_choose_text": {
    "string": ""
  },
  "pin_retype_header": {
    "string": ""
  },
  "pin_retype_text": {
    "string": ""
  },
  "pin_not_match": {
    "string": ""
  },
  "pin_disable_title": {
    "string": ""
  },
  "pin_disable_text": {
    "string": ""
  },
  "pin_disable_button": {
    "string": ""
  },
  "pin_enter": {
    "string": ""
  },
  "pin_last_attempt": {
    "string": ""
  },
  "pin_attempts": {
    "string": ""
  },
  "pin_forgot_title": {
    "string": ""
  },
  "pin_forgot_text": {
    "string": ""
  },
  "pin_forgot_reset": {
    "string": ""
  },
  "pin_send": {
    "string": ""
  },
  "pin_send_title": {
    "string": ""
  },
  "pin_use_biometrics": {
    "string": ""
  },
  "bio": {
    "string": ""
  },
  "bio_auth_with": {
    "string": ""
  },
  "bio_no": {
    "string": ""
  },
  "bio_face_id": {
    "string": ""
  },
  "bio_touch_id": {
    "string": ""
  },
  "bio_confirm": {
    "string": ""
  },
  "bio_error_title": {
    "string": ""
  },
  "bio_error_message": {
    "string": ""
  },
  "bio_loading": {
    "string": ""
  },
  "bio_not_available": {
    "string": ""
  },
  "bio_ask": {
    "string": ""
  },
  "bio_use": {
    "string": ""
  },
  "bio_phone_settings": {
    "string": ""
  },
  "success_title": {
    "string": ""
  },
  "success_bio": {
    "string": ""
  },
  "success_no_bio": {
    "string": ""
  },
  "success_payments": {
    "string": ""
  },
  "reset_title": {
    "string": ""
  },
  "reset_text": {
    "string": ""
  },
  "reset_button_backup": {
    "string": ""
  },
  "reset_button_reset": {
    "string": ""
  },
  "reset_dialog_title": {
    "string": ""
  },
  "reset_dialog_desc": {
    "string": ""
  },
  "reset_confirm": {
    "string": ""
  },
  "recovery": {
    "string": ""
  },
  "recovery_text": {
    "string": ""
  },
  "display_seed": {
    "string": ""
  },
  "contact_support": {
    "string": ""
  },
  "wipe_app": {
    "string": ""
  },
  "close_app": {
    "string": ""
  },
  "export_title": {
    "string": ""
  },
  "export_text": {
    "string": ""
  },
  "export_password": {
    "string": ""
  },
  "export_button": {
    "string": ""
  },
  "export_share": {
    "string": ""
  },
  "export_success_title": {
    "string": ""
  },
  "export_success_msg": {
    "string": ""
  },
  "export_error_title": {
    "string": ""
  },
  "export_error_msg": {
    "string": ""
  },
  "export_error_file": {
    "string": ""
  },
  "cp_title": {
    "string": ""
  },
  "cp_text": {
    "string": ""
  },
  "cp_retype_title": {
    "string": ""
  },
  "cp_retype_text": {
    "string": ""
  },
  "cp_setnew_title": {
    "string": ""
  },
  "cp_setnew_text": {
    "string": ""
  },
  "cp_try_again": {
    "string": ""
  },
  "cp_changed_title": {
    "string": ""
  },
  "cp_changed_text": {
    "string": ""
  },
  "use_pin": {
    "string": ""
  },
  "wiped_title": {
    "string": ""
  },
  "wiped_message": {
    "string": ""
  },
  "authorization": {
    "title": {
      "string": ""
    },
    "description": {
      "string": ""
    },
    "authorize": {
      "string": ""
    },
    "deny": {
      "string": ""
    },
    "authorizing": {
      "string": ""
    },
    "success": {
      "string": ""
    },
    "claims": {
      "string": ""
    },
    "requested_permissions": {
      "string": ""
    },
    "pubky_secret_error_title": {
      "string": ""
    },
    "pubky_secret_error_description": {
      "string": ""
    },
    "pubky_auth_error_title": {
        "string": ""
        },
    "pubky_auth_error_description": {
        "string": ""
    }
  }
}
